{
    "name": "Sparkbit",
    "version": "0.0.0",
    "description": "Microsoft MakeCode package for Kid Spark Education Spark:bit programmable robotics platform.",
    "license": "MIT",
    "dependencies": {
        "core": "*",
        "radio": "*",
        "microphone": "*"
    },
    "files": [
        "README.md",
        "sparkbit.ts",
        "_locales/es-ES/Sparkbit-strings.json",
        "_locales/es-ES/Sparkbit-jsdoc-strings.json"
    ],
    "testFiles": [
        "test.ts"
    ],
    "targetVersions": {
        "target": "4.0.12",
        "targetId": "microbit"
    },
    "supportedTargets": [
        "microbit"
    ],
    "disablesVariants": [
        "mbdal"
    ]
}
